{
  "schemaVersion": 1,
  "generatedAt": "2026-05-18T09:49:07+09:00",
  "logEntryCount": 566,
  "recent24h": {
    "forecast": {
      "lead30": {
        "mae_total": 6.48,
        "mae_per_stall": [
          2.215,
          1.88,
          2.07,
          1.41
        ],
        "n": 476
      },
      "lead60": {
        "mae_total": 6.32,
        "mae_per_stall": [
          2.34,
          2.035,
          1.795,
          1.32
        ],
        "n": 459
      },
      "lead120": {
        "mae_total": 8.615,
        "mae_per_stall": [
          2.525,
          2.79,
          2.405,
          2.055
        ],
        "n": 285
      }
    },
    "patternMatch": {
      "lead30": {
        "mae_total": 5.065,
        "mae_per_stall": [
          1.89,
          1.65,
          1.325,
          1.08
        ],
        "n": 476
      },
      "lead60": {
        "mae_total": 5.315,
        "mae_per_stall": [
          1.905,
          1.71,
          1.385,
          1.12
        ],
        "n": 459
      },
      "lead120": {
        "mae_total": 5.455,
        "mae_per_stall": [
          1.77,
          1.805,
          1.51,
          1.14
        ],
        "n": 285
      }
    },
    "winner": {
      "lead30": "patternMatch",
      "lead60": "patternMatch",
      "lead120": "patternMatch"
    }
  },
  "allPeriod": {
    "forecast": {
      "lead30": {
        "mae_total": 6.135,
        "mae_per_stall": [
          2.21,
          1.845,
          1.89,
          1.5
        ],
        "n": 1000
      },
      "lead60": {
        "mae_total": 5.89,
        "mae_per_stall": [
          2.27,
          1.79,
          1.765,
          1.42
        ],
        "n": 984
      },
      "lead120": {
        "mae_total": 6.945,
        "mae_per_stall": [
          2.575,
          2.22,
          2.04,
          1.9
        ],
        "n": 637
      }
    },
    "patternMatch": {
      "lead30": {
        "mae_total": 4.92,
        "mae_per_stall": [
          1.93,
          1.6,
          1.475,
          1.185
        ],
        "n": 1000
      },
      "lead60": {
        "mae_total": 5.02,
        "mae_per_stall": [
          1.925,
          1.575,
          1.5,
          1.18
        ],
        "n": 984
      },
      "lead120": {
        "mae_total": 5.08,
        "mae_per_stall": [
          1.885,
          1.56,
          1.56,
          1.215
        ],
        "n": 637
      }
    },
    "winner": {
      "lead30": "patternMatch",
      "lead60": "patternMatch",
      "lead120": "patternMatch"
    }
  },
  "throughputScaleK": 5
}
