{
  "schemaVersion": 1,
  "generatedAt": "2026-05-18T15:48:07+09:00",
  "logEntryCount": 635,
  "recent24h": {
    "forecast": {
      "lead30": {
        "mae_total": 6.6,
        "mae_per_stall": [
          2.105,
          1.83,
          2.24,
          1.62
        ],
        "n": 475
      },
      "lead60": {
        "mae_total": 6.53,
        "mae_per_stall": [
          2.35,
          2.025,
          1.99,
          1.61
        ],
        "n": 457
      },
      "lead120": {
        "mae_total": 9.145,
        "mae_per_stall": [
          3.04,
          2.76,
          2.675,
          2.24
        ],
        "n": 286
      }
    },
    "patternMatch": {
      "lead30": {
        "mae_total": 5.265,
        "mae_per_stall": [
          1.84,
          1.675,
          1.56,
          1.41
        ],
        "n": 475
      },
      "lead60": {
        "mae_total": 5.46,
        "mae_per_stall": [
          1.99,
          1.74,
          1.62,
          1.38
        ],
        "n": 457
      },
      "lead120": {
        "mae_total": 5.75,
        "mae_per_stall": [
          2.01,
          1.855,
          1.695,
          1.485
        ],
        "n": 286
      }
    },
    "winner": {
      "lead30": "patternMatch",
      "lead60": "patternMatch",
      "lead120": "patternMatch"
    }
  },
  "allPeriod": {
    "forecast": {
      "lead30": {
        "mae_total": 6.225,
        "mae_per_stall": [
          2.36,
          1.83,
          1.83,
          1.61
        ],
        "n": 1198
      },
      "lead60": {
        "mae_total": 6.005,
        "mae_per_stall": [
          2.41,
          1.835,
          1.725,
          1.545
        ],
        "n": 1182
      },
      "lead120": {
        "mae_total": 7.155,
        "mae_per_stall": [
          2.775,
          2.275,
          2.045,
          1.985
        ],
        "n": 770
      }
    },
    "patternMatch": {
      "lead30": {
        "mae_total": 5,
        "mae_per_stall": [
          2.09,
          1.615,
          1.45,
          1.31
        ],
        "n": 1198
      },
      "lead60": {
        "mae_total": 5.08,
        "mae_per_stall": [
          2.1,
          1.605,
          1.475,
          1.28
        ],
        "n": 1182
      },
      "lead120": {
        "mae_total": 5.15,
        "mae_per_stall": [
          2.06,
          1.595,
          1.53,
          1.34
        ],
        "n": 770
      }
    },
    "winner": {
      "lead30": "patternMatch",
      "lead60": "patternMatch",
      "lead120": "patternMatch"
    }
  },
  "throughputScaleK": 5
}
