{
  "schemaVersion": 1,
  "generatedAt": "2026-05-20T16:21:46+09:00",
  "logEntryCount": 1193,
  "recent24h": {
    "forecast": {
      "lead30": {
        "mae_total": 17.745,
        "mae_per_stall": [
          5.77,
          2.53,
          4.74,
          7.165
        ],
        "n": 466
      },
      "lead60": {
        "mae_total": 15.325,
        "mae_per_stall": [
          5.11,
          2.28,
          4.34,
          5.94
        ],
        "n": 453
      },
      "lead120": {
        "mae_total": 12.595,
        "mae_per_stall": [
          3.395,
          1.985,
          3.795,
          6
        ],
        "n": 282
      }
    },
    "patternMatch": {
      "lead30": {
        "mae_total": 4.55,
        "mae_per_stall": [
          2.105,
          1.39,
          1.155,
          1.405
        ],
        "n": 466
      },
      "lead60": {
        "mae_total": 4.425,
        "mae_per_stall": [
          2.02,
          1.405,
          1.125,
          1.395
        ],
        "n": 453
      },
      "lead120": {
        "mae_total": 4.145,
        "mae_per_stall": [
          2.01,
          1.355,
          1.05,
          1.295
        ],
        "n": 282
      }
    },
    "winner": {
      "lead30": "patternMatch",
      "lead60": "patternMatch",
      "lead120": "patternMatch"
    }
  },
  "allPeriod": {
    "forecast": {
      "lead30": {
        "mae_total": 11.565,
        "mae_per_stall": [
          4.445,
          2.035,
          2.61,
          4.26
        ],
        "n": 2185
      },
      "lead60": {
        "mae_total": 10.61,
        "mae_per_stall": [
          4.17,
          1.96,
          2.345,
          3.93
        ],
        "n": 2175
      },
      "lead120": {
        "mae_total": 11.22,
        "mae_per_stall": [
          4.36,
          2.13,
          2.39,
          4.495
        ],
        "n": 1439
      }
    },
    "patternMatch": {
      "lead30": {
        "mae_total": 5.07,
        "mae_per_stall": [
          2.125,
          1.56,
          1.475,
          1.27
        ],
        "n": 2185
      },
      "lead60": {
        "mae_total": 5.075,
        "mae_per_stall": [
          2.12,
          1.54,
          1.465,
          1.25
        ],
        "n": 2175
      },
      "lead120": {
        "mae_total": 5.06,
        "mae_per_stall": [
          2.1,
          1.525,
          1.48,
          1.265
        ],
        "n": 1439
      }
    },
    "winner": {
      "lead30": "patternMatch",
      "lead60": "patternMatch",
      "lead120": "patternMatch"
    }
  },
  "throughputScaleK": 5
}
