{
  "schemaVersion": 1,
  "generatedAt": "2026-05-21T13:19:22+09:00",
  "logEntryCount": 1433,
  "recent24h": {
    "forecast": {
      "lead30": {
        "mae_total": 35.28,
        "mae_per_stall": [
          8.58,
          9.335,
          11.32,
          7.74
        ],
        "n": 462
      },
      "lead60": {
        "mae_total": 34.185,
        "mae_per_stall": [
          8.165,
          8.93,
          11.435,
          7.465
        ],
        "n": 447
      },
      "lead120": {
        "mae_total": 33.185,
        "mae_per_stall": [
          8.215,
          9.18,
          9.6,
          7.51
        ],
        "n": 279
      }
    },
    "patternMatch": {
      "lead30": {
        "mae_total": 4.205,
        "mae_per_stall": [
          1.78,
          1.23,
          1.38,
          1.395
        ],
        "n": 462
      },
      "lead60": {
        "mae_total": 4.26,
        "mae_per_stall": [
          1.77,
          1.275,
          1.36,
          1.405
        ],
        "n": 447
      },
      "lead120": {
        "mae_total": 4.02,
        "mae_per_stall": [
          1.69,
          1.21,
          1.185,
          1.355
        ],
        "n": 279
      }
    },
    "winner": {
      "lead30": "patternMatch",
      "lead60": "patternMatch",
      "lead120": "patternMatch"
    }
  },
  "allPeriod": {
    "forecast": {
      "lead30": {
        "mae_total": 15.735,
        "mae_per_stall": [
          5.275,
          3.3,
          3.92,
          4.935
        ],
        "n": 2566
      },
      "lead60": {
        "mae_total": 14.615,
        "mae_per_stall": [
          4.935,
          3.13,
          3.69,
          4.59
        ],
        "n": 2553
      },
      "lead120": {
        "mae_total": 14.715,
        "mae_per_stall": [
          5.03,
          3.245,
          3.425,
          5
        ],
        "n": 1695
      }
    },
    "patternMatch": {
      "lead30": {
        "mae_total": 4.935,
        "mae_per_stall": [
          2.055,
          1.51,
          1.44,
          1.28
        ],
        "n": 2566
      },
      "lead60": {
        "mae_total": 4.95,
        "mae_per_stall": [
          2.055,
          1.5,
          1.43,
          1.27
        ],
        "n": 2553
      },
      "lead120": {
        "mae_total": 4.92,
        "mae_per_stall": [
          2.035,
          1.485,
          1.43,
          1.28
        ],
        "n": 1695
      }
    },
    "winner": {
      "lead30": "patternMatch",
      "lead60": "patternMatch",
      "lead120": "patternMatch"
    }
  },
  "throughputScaleK": 5
}
