{
  "schemaVersion": 1,
  "generatedAt": "2026-05-21T04:03:23+09:00",
  "logEntryCount": 1327,
  "recent24h": {
    "forecast": {
      "lead30": {
        "mae_total": 13.355,
        "mae_per_stall": [
          2.01,
          2.355,
          6.76,
          5
        ],
        "n": 473
      },
      "lead60": {
        "mae_total": 13.185,
        "mae_per_stall": [
          2.01,
          2.195,
          7.395,
          4.41
        ],
        "n": 456
      },
      "lead120": {
        "mae_total": 13.58,
        "mae_per_stall": [
          2.14,
          2.35,
          6.7,
          5.455
        ],
        "n": 286
      }
    },
    "patternMatch": {
      "lead30": {
        "mae_total": 3.985,
        "mae_per_stall": [
          1.955,
          1.21,
          1.11,
          1.23
        ],
        "n": 473
      },
      "lead60": {
        "mae_total": 3.815,
        "mae_per_stall": [
          1.91,
          1.205,
          1.1,
          1.18
        ],
        "n": 456
      },
      "lead120": {
        "mae_total": 3.91,
        "mae_per_stall": [
          2.11,
          1.33,
          1.02,
          1.175
        ],
        "n": 286
      }
    },
    "winner": {
      "lead30": "patternMatch",
      "lead60": "patternMatch",
      "lead120": "patternMatch"
    }
  },
  "allPeriod": {
    "forecast": {
      "lead30": {
        "mae_total": 12.07,
        "mae_per_stall": [
          4.38,
          2.09,
          3.115,
          4.33
        ],
        "n": 2269
      },
      "lead60": {
        "mae_total": 11.275,
        "mae_per_stall": [
          4.115,
          2,
          2.995,
          4.02
        ],
        "n": 2256
      },
      "lead120": {
        "mae_total": 11.625,
        "mae_per_stall": [
          4.27,
          2.165,
          2.9,
          4.465
        ],
        "n": 1495
      }
    },
    "patternMatch": {
      "lead30": {
        "mae_total": 5.045,
        "mae_per_stall": [
          2.115,
          1.535,
          1.48,
          1.275
        ],
        "n": 2269
      },
      "lead60": {
        "mae_total": 5.05,
        "mae_per_stall": [
          2.105,
          1.515,
          1.47,
          1.255
        ],
        "n": 2256
      },
      "lead120": {
        "mae_total": 5.035,
        "mae_per_stall": [
          2.09,
          1.505,
          1.48,
          1.27
        ],
        "n": 1495
      }
    },
    "winner": {
      "lead30": "patternMatch",
      "lead60": "patternMatch",
      "lead120": "patternMatch"
    }
  },
  "throughputScaleK": 5
}
