{
  "schemaVersion": 1,
  "generatedAt": "2026-05-17T05:01:45+09:00",
  "logEntryCount": 234,
  "recent24h": {
    "forecast": {
      "lead30": {
        "mae_total": 1.359,
        "mae_per_stall": [
          0.537,
          0.425,
          0.368,
          0.414
        ],
        "n": 348
      },
      "lead60": {
        "mae_total": 1.211,
        "mae_per_stall": [
          0.479,
          0.351,
          0.408,
          0.396
        ],
        "n": 336
      },
      "lead120": {
        "mae_total": 1.149,
        "mae_per_stall": [
          0.488,
          0.333,
          0.403,
          0.473
        ],
        "n": 201
      }
    },
    "patternMatch": {
      "lead30": {
        "mae_total": 1.129,
        "mae_per_stall": [
          0.471,
          0.376,
          0.333,
          0.351
        ],
        "n": 348
      },
      "lead60": {
        "mae_total": 1.131,
        "mae_per_stall": [
          0.452,
          0.348,
          0.342,
          0.339
        ],
        "n": 336
      },
      "lead120": {
        "mae_total": 1.169,
        "mae_per_stall": [
          0.433,
          0.333,
          0.383,
          0.368
        ],
        "n": 201
      }
    },
    "winner": {
      "lead30": "patternMatch",
      "lead60": "patternMatch",
      "lead120": "forecast"
    }
  },
  "allPeriod": {
    "forecast": {
      "lead30": {
        "mae_total": 1.359,
        "mae_per_stall": [
          0.537,
          0.425,
          0.368,
          0.414
        ],
        "n": 348
      },
      "lead60": {
        "mae_total": 1.211,
        "mae_per_stall": [
          0.479,
          0.351,
          0.408,
          0.396
        ],
        "n": 336
      },
      "lead120": {
        "mae_total": 1.149,
        "mae_per_stall": [
          0.488,
          0.333,
          0.403,
          0.473
        ],
        "n": 201
      }
    },
    "patternMatch": {
      "lead30": {
        "mae_total": 1.129,
        "mae_per_stall": [
          0.471,
          0.376,
          0.333,
          0.351
        ],
        "n": 348
      },
      "lead60": {
        "mae_total": 1.131,
        "mae_per_stall": [
          0.452,
          0.348,
          0.342,
          0.339
        ],
        "n": 336
      },
      "lead120": {
        "mae_total": 1.169,
        "mae_per_stall": [
          0.433,
          0.333,
          0.383,
          0.368
        ],
        "n": 201
      }
    },
    "winner": {
      "lead30": "patternMatch",
      "lead60": "patternMatch",
      "lead120": "forecast"
    }
  }
}
