{
  "schemaVersion": 1,
  "generatedAt": "2026-05-16T06:02:08+09:00",
  "trendFactor": 0.6,
  "trendWindow": {
    "actual": 2,
    "expected": 3.3333333333333335,
    "ticks": 12
  },
  "baselineSampleCount": 542,
  "slots": [
    {
      "slotStart": "06:05",
      "slotEnd": "06:10",
      "flightFactor": 2.181818181818182,
      "stall1": 0,
      "stall2": 0,
      "stall3": 1,
      "stall4": 0,
      "total": 1
    },
    {
      "slotStart": "06:10",
      "slotEnd": "06:15",
      "flightFactor": 0.3,
      "stall1": 0,
      "stall2": 0,
      "stall3": 0,
      "stall4": 0,
      "total": 0
    },
    {
      "slotStart": "06:15",
      "slotEnd": "06:20",
      "flightFactor": 0.3,
      "stall1": 0,
      "stall2": 0,
      "stall3": 0,
      "stall4": 0,
      "total": 0
    },
    {
      "slotStart": "06:20",
      "slotEnd": "06:25",
      "flightFactor": 0.3,
      "stall1": 0,
      "stall2": 0,
      "stall3": 0,
      "stall4": 0,
      "total": 0
    },
    {
      "slotStart": "06:25",
      "slotEnd": "06:30",
      "flightFactor": 1.7454545454545456,
      "stall1": 0,
      "stall2": 0,
      "stall3": 0,
      "stall4": 0,
      "total": 0
    },
    {
      "slotStart": "06:30",
      "slotEnd": "06:35",
      "flightFactor": 0.3,
      "stall1": 0,
      "stall2": 0,
      "stall3": 0,
      "stall4": 0,
      "total": 0
    },
    {
      "slotStart": "06:35",
      "slotEnd": "06:40",
      "flightFactor": 3,
      "stall1": 0,
      "stall2": 0,
      "stall3": 0,
      "stall4": 0,
      "total": 0
    },
    {
      "slotStart": "06:40",
      "slotEnd": "06:45",
      "flightFactor": 0.3,
      "stall1": 0,
      "stall2": 0,
      "stall3": 0,
      "stall4": 0,
      "total": 0
    },
    {
      "slotStart": "06:45",
      "slotEnd": "06:50",
      "flightFactor": 1.7454545454545456,
      "stall1": 0,
      "stall2": 0,
      "stall3": 2,
      "stall4": 0,
      "total": 2
    },
    {
      "slotStart": "06:50",
      "slotEnd": "06:55",
      "flightFactor": 2.181818181818182,
      "stall1": 0,
      "stall2": 0,
      "stall3": 0,
      "stall4": 0,
      "total": 0
    },
    {
      "slotStart": "06:55",
      "slotEnd": "07:00",
      "flightFactor": 0.3,
      "stall1": 0,
      "stall2": 0,
      "stall3": 0,
      "stall4": 0,
      "total": 0
    },
    {
      "slotStart": "07:00",
      "slotEnd": "07:05",
      "flightFactor": 3,
      "stall1": 0,
      "stall2": 0,
      "stall3": 0,
      "stall4": 0,
      "total": 0
    },
    {
      "slotStart": "07:05",
      "slotEnd": "07:10",
      "flightFactor": 0.3,
      "stall1": 0,
      "stall2": 0,
      "stall3": 0,
      "stall4": 0,
      "total": 0
    },
    {
      "slotStart": "07:10",
      "slotEnd": "07:15",
      "flightFactor": 0.3,
      "stall1": 0,
      "stall2": 0,
      "stall3": 0,
      "stall4": 0,
      "total": 0
    },
    {
      "slotStart": "07:15",
      "slotEnd": "07:20",
      "flightFactor": 0.3,
      "stall1": 0,
      "stall2": 0,
      "stall3": 0,
      "stall4": 0,
      "total": 0
    },
    {
      "slotStart": "07:20",
      "slotEnd": "07:25",
      "flightFactor": 0.3,
      "stall1": 0,
      "stall2": 0,
      "stall3": 0,
      "stall4": 0,
      "total": 0
    },
    {
      "slotStart": "07:25",
      "slotEnd": "07:30",
      "flightFactor": 0.3,
      "stall1": 0,
      "stall2": 0,
      "stall3": 0,
      "stall4": 0,
      "total": 0
    },
    {
      "slotStart": "07:30",
      "slotEnd": "07:35",
      "flightFactor": 0.3,
      "stall1": 0,
      "stall2": 0,
      "stall3": 0,
      "stall4": 0,
      "total": 0
    },
    {
      "slotStart": "07:35",
      "slotEnd": "07:40",
      "flightFactor": 0.3,
      "stall1": 0,
      "stall2": 0,
      "stall3": 0,
      "stall4": 0,
      "total": 0
    },
    {
      "slotStart": "07:40",
      "slotEnd": "07:45",
      "flightFactor": 1.309090909090909,
      "stall1": 0,
      "stall2": 0,
      "stall3": 0,
      "stall4": 0,
      "total": 0
    },
    {
      "slotStart": "07:45",
      "slotEnd": "07:50",
      "flightFactor": 3,
      "stall1": 0,
      "stall2": 0,
      "stall3": 0,
      "stall4": 1,
      "total": 1
    },
    {
      "slotStart": "07:50",
      "slotEnd": "07:55",
      "flightFactor": 3,
      "stall1": 0,
      "stall2": 0,
      "stall3": 0,
      "stall4": 0,
      "total": 0
    },
    {
      "slotStart": "07:55",
      "slotEnd": "08:00",
      "flightFactor": 0.3,
      "stall1": 0,
      "stall2": 0,
      "stall3": 0,
      "stall4": 0,
      "total": 0
    },
    {
      "slotStart": "08:00",
      "slotEnd": "08:05",
      "flightFactor": 0.3,
      "stall1": 0,
      "stall2": 0,
      "stall3": 0,
      "stall4": 0,
      "total": 0
    }
  ]
}
