{
  "schemaVersion": 1,
  "generatedAt": "2026-05-17T15:37:03+09:00",
  "trendFactor": 1.0333333333333334,
  "trendWindow": {
    "actual": 93,
    "expected": 18,
    "ticks": 12,
    "source": "track",
    "k": 5
  },
  "baselineSampleCount": 823,
  "slots": [
    {
      "slotStart": "15:40",
      "slotEnd": "15:45",
      "flightFactor": 1.0285714285714285,
      "stall1": 5,
      "stall2": 0,
      "stall3": 0,
      "stall4": 0,
      "total": 5
    },
    {
      "slotStart": "15:45",
      "slotEnd": "15:50",
      "flightFactor": 0.8,
      "stall1": 0,
      "stall2": 0,
      "stall3": 0,
      "stall4": 0,
      "total": 0
    },
    {
      "slotStart": "15:50",
      "slotEnd": "15:55",
      "flightFactor": 0.5714285714285714,
      "stall1": 5,
      "stall2": 0,
      "stall3": 0,
      "stall4": 0,
      "total": 5
    },
    {
      "slotStart": "15:55",
      "slotEnd": "16:00",
      "flightFactor": 1.6,
      "stall1": 5,
      "stall2": 5,
      "stall3": 0,
      "stall4": 0,
      "total": 10
    },
    {
      "slotStart": "16:00",
      "slotEnd": "16:05",
      "flightFactor": 0.3,
      "stall1": 0,
      "stall2": 0,
      "stall3": 0,
      "stall4": 0,
      "total": 0
    },
    {
      "slotStart": "16:05",
      "slotEnd": "16:10",
      "flightFactor": 0.5714285714285714,
      "stall1": 0,
      "stall2": 0,
      "stall3": 0,
      "stall4": 0,
      "total": 0
    },
    {
      "slotStart": "16:10",
      "slotEnd": "16:15",
      "flightFactor": 3,
      "stall1": 0,
      "stall2": 10,
      "stall3": 0,
      "stall4": 0,
      "total": 10
    },
    {
      "slotStart": "16:15",
      "slotEnd": "16:20",
      "flightFactor": 2.2857142857142856,
      "stall1": 10,
      "stall2": 5,
      "stall3": 0,
      "stall4": 0,
      "total": 15
    },
    {
      "slotStart": "16:20",
      "slotEnd": "16:25",
      "flightFactor": 0.8,
      "stall1": 0,
      "stall2": 0,
      "stall3": 0,
      "stall4": 0,
      "total": 0
    },
    {
      "slotStart": "16:25",
      "slotEnd": "16:30",
      "flightFactor": 0.3,
      "stall1": 0,
      "stall2": 0,
      "stall3": 0,
      "stall4": 0,
      "total": 0
    },
    {
      "slotStart": "16:30",
      "slotEnd": "16:35",
      "flightFactor": 0.3,
      "stall1": 0,
      "stall2": 0,
      "stall3": 0,
      "stall4": 0,
      "total": 0
    },
    {
      "slotStart": "16:35",
      "slotEnd": "16:40",
      "flightFactor": 0.8,
      "stall1": 5,
      "stall2": 0,
      "stall3": 5,
      "stall4": 0,
      "total": 10
    },
    {
      "slotStart": "16:40",
      "slotEnd": "16:45",
      "flightFactor": 1.8285714285714285,
      "stall1": 0,
      "stall2": 0,
      "stall3": 0,
      "stall4": 5,
      "total": 5
    },
    {
      "slotStart": "16:45",
      "slotEnd": "16:50",
      "flightFactor": 0.3,
      "stall1": 0,
      "stall2": 0,
      "stall3": 0,
      "stall4": 0,
      "total": 0
    },
    {
      "slotStart": "16:50",
      "slotEnd": "16:55",
      "flightFactor": 0.45714285714285713,
      "stall1": 0,
      "stall2": 0,
      "stall3": 0,
      "stall4": 0,
      "total": 0
    },
    {
      "slotStart": "16:55",
      "slotEnd": "17:00",
      "flightFactor": 0.9142857142857143,
      "stall1": 0,
      "stall2": 0,
      "stall3": 0,
      "stall4": 0,
      "total": 0
    },
    {
      "slotStart": "17:00",
      "slotEnd": "17:05",
      "flightFactor": 0.45714285714285713,
      "stall1": 0,
      "stall2": 0,
      "stall3": 0,
      "stall4": 0,
      "total": 0
    },
    {
      "slotStart": "17:05",
      "slotEnd": "17:10",
      "flightFactor": 1.1428571428571428,
      "stall1": 5,
      "stall2": 0,
      "stall3": 0,
      "stall4": 0,
      "total": 5
    },
    {
      "slotStart": "17:10",
      "slotEnd": "17:15",
      "flightFactor": 3,
      "stall1": 5,
      "stall2": 0,
      "stall3": 0,
      "stall4": 0,
      "total": 5
    },
    {
      "slotStart": "17:15",
      "slotEnd": "17:20",
      "flightFactor": 0.6857142857142857,
      "stall1": 0,
      "stall2": 0,
      "stall3": 0,
      "stall4": 0,
      "total": 0
    },
    {
      "slotStart": "17:20",
      "slotEnd": "17:25",
      "flightFactor": 0.3,
      "stall1": 0,
      "stall2": 0,
      "stall3": 0,
      "stall4": 0,
      "total": 0
    },
    {
      "slotStart": "17:25",
      "slotEnd": "17:30",
      "flightFactor": 1.3714285714285714,
      "stall1": 0,
      "stall2": 0,
      "stall3": 0,
      "stall4": 0,
      "total": 0
    },
    {
      "slotStart": "17:30",
      "slotEnd": "17:35",
      "flightFactor": 0.34285714285714286,
      "stall1": 0,
      "stall2": 0,
      "stall3": 0,
      "stall4": 0,
      "total": 0
    },
    {
      "slotStart": "17:35",
      "slotEnd": "17:40",
      "flightFactor": 1.0285714285714285,
      "stall1": 5,
      "stall2": 0,
      "stall3": 0,
      "stall4": 0,
      "total": 5
    }
  ],
  "throughputScaleK": 5
}
