{
  "schemaVersion": 1,
  "generatedAt": "2026-05-20T15:29:09+09:00",
  "trendFactor": 1.1162790697674418,
  "trendWindow": {
    "actual": 18,
    "expected": 16.125,
    "ticks": 12,
    "levelSource": "track-anchored"
  },
  "baselineSampleCount": 1331,
  "slots": [
    {
      "slotStart": "15:30",
      "slotEnd": "15:35",
      "flightFactor": 0.3,
      "stall1": 0,
      "stall2": 0,
      "stall3": 1,
      "stall4": 0,
      "total": 1
    },
    {
      "slotStart": "15:35",
      "slotEnd": "15:40",
      "flightFactor": 0.6605504587155963,
      "stall1": 0,
      "stall2": 0,
      "stall3": 2,
      "stall4": 1,
      "total": 3
    },
    {
      "slotStart": "15:40",
      "slotEnd": "15:45",
      "flightFactor": 0.4403669724770642,
      "stall1": 0,
      "stall2": 0,
      "stall3": 1,
      "stall4": 0,
      "total": 1
    },
    {
      "slotStart": "15:45",
      "slotEnd": "15:50",
      "flightFactor": 0.3,
      "stall1": 0,
      "stall2": 0,
      "stall3": 1,
      "stall4": 0,
      "total": 1
    },
    {
      "slotStart": "15:50",
      "slotEnd": "15:55",
      "flightFactor": 0.4403669724770642,
      "stall1": 0,
      "stall2": 0,
      "stall3": 1,
      "stall4": 0,
      "total": 1
    },
    {
      "slotStart": "15:55",
      "slotEnd": "16:00",
      "flightFactor": 1.9816513761467889,
      "stall1": 0,
      "stall2": 1,
      "stall3": 6,
      "stall4": 2,
      "total": 9
    },
    {
      "slotStart": "16:00",
      "slotEnd": "16:05",
      "flightFactor": 1.1009174311926604,
      "stall1": 0,
      "stall2": 0,
      "stall3": 3,
      "stall4": 1,
      "total": 4
    },
    {
      "slotStart": "16:05",
      "slotEnd": "16:10",
      "flightFactor": 0.3,
      "stall1": 0,
      "stall2": 0,
      "stall3": 1,
      "stall4": 0,
      "total": 1
    },
    {
      "slotStart": "16:10",
      "slotEnd": "16:15",
      "flightFactor": 2.311926605504587,
      "stall1": 0,
      "stall2": 1,
      "stall3": 7,
      "stall4": 2,
      "total": 10
    },
    {
      "slotStart": "16:15",
      "slotEnd": "16:20",
      "flightFactor": 1.7614678899082568,
      "stall1": 0,
      "stall2": 1,
      "stall3": 5,
      "stall4": 1,
      "total": 7
    },
    {
      "slotStart": "16:20",
      "slotEnd": "16:25",
      "flightFactor": 1.8715596330275228,
      "stall1": 0,
      "stall2": 1,
      "stall3": 6,
      "stall4": 2,
      "total": 9
    },
    {
      "slotStart": "16:25",
      "slotEnd": "16:30",
      "flightFactor": 0.6605504587155963,
      "stall1": 0,
      "stall2": 0,
      "stall3": 2,
      "stall4": 1,
      "total": 3
    },
    {
      "slotStart": "16:30",
      "slotEnd": "16:35",
      "flightFactor": 0.6605504587155963,
      "stall1": 0,
      "stall2": 0,
      "stall3": 2,
      "stall4": 1,
      "total": 3
    },
    {
      "slotStart": "16:35",
      "slotEnd": "16:40",
      "flightFactor": 0.4403669724770642,
      "stall1": 0,
      "stall2": 0,
      "stall3": 1,
      "stall4": 0,
      "total": 1
    },
    {
      "slotStart": "16:40",
      "slotEnd": "16:45",
      "flightFactor": 0.3,
      "stall1": 0,
      "stall2": 0,
      "stall3": 1,
      "stall4": 0,
      "total": 1
    },
    {
      "slotStart": "16:45",
      "slotEnd": "16:50",
      "flightFactor": 1.9816513761467889,
      "stall1": 0,
      "stall2": 1,
      "stall3": 6,
      "stall4": 2,
      "total": 9
    },
    {
      "slotStart": "16:50",
      "slotEnd": "16:55",
      "flightFactor": 0.3,
      "stall1": 0,
      "stall2": 0,
      "stall3": 1,
      "stall4": 0,
      "total": 1
    },
    {
      "slotStart": "16:55",
      "slotEnd": "17:00",
      "flightFactor": 0.4403669724770642,
      "stall1": 0,
      "stall2": 0,
      "stall3": 1,
      "stall4": 0,
      "total": 1
    },
    {
      "slotStart": "17:00",
      "slotEnd": "17:05",
      "flightFactor": 0.6605504587155963,
      "stall1": 0,
      "stall2": 0,
      "stall3": 2,
      "stall4": 1,
      "total": 3
    },
    {
      "slotStart": "17:05",
      "slotEnd": "17:10",
      "flightFactor": 1.7614678899082568,
      "stall1": 0,
      "stall2": 1,
      "stall3": 5,
      "stall4": 1,
      "total": 7
    },
    {
      "slotStart": "17:10",
      "slotEnd": "17:15",
      "flightFactor": 0.9908256880733944,
      "stall1": 0,
      "stall2": 0,
      "stall3": 3,
      "stall4": 1,
      "total": 4
    },
    {
      "slotStart": "17:15",
      "slotEnd": "17:20",
      "flightFactor": 1.4311926605504586,
      "stall1": 0,
      "stall2": 0,
      "stall3": 4,
      "stall4": 1,
      "total": 5
    },
    {
      "slotStart": "17:20",
      "slotEnd": "17:25",
      "flightFactor": 1.3211009174311925,
      "stall1": 0,
      "stall2": 0,
      "stall3": 4,
      "stall4": 1,
      "total": 5
    },
    {
      "slotStart": "17:25",
      "slotEnd": "17:30",
      "flightFactor": 2.422018348623853,
      "stall1": 0,
      "stall2": 1,
      "stall3": 7,
      "stall4": 2,
      "total": 10
    }
  ],
  "throughputScaleK": 1
}
