{
  "schemaVersion": 1,
  "generatedAt": "2026-05-17T21:35:52+09:00",
  "trendFactor": 1,
  "trendWindow": {
    "actual": 0,
    "expected": 0,
    "ticks": 12,
    "source": "netdiff",
    "k": null
  },
  "baselineSampleCount": 862,
  "slots": [
    {
      "slotStart": "21:40",
      "slotEnd": "21:45",
      "flightFactor": 2.6666666666666665,
      "stall1": 0,
      "stall2": 0,
      "stall3": 0,
      "stall4": 0,
      "total": 0
    },
    {
      "slotStart": "21:45",
      "slotEnd": "21:50",
      "flightFactor": 0.3,
      "stall1": 0,
      "stall2": 0,
      "stall3": 0,
      "stall4": 0,
      "total": 0
    },
    {
      "slotStart": "21:50",
      "slotEnd": "21:55",
      "flightFactor": 1.1851851851851851,
      "stall1": 0,
      "stall2": 0,
      "stall3": 0,
      "stall4": 0,
      "total": 0
    },
    {
      "slotStart": "21:55",
      "slotEnd": "22:00",
      "flightFactor": 1.382716049382716,
      "stall1": 0,
      "stall2": 0,
      "stall3": 0,
      "stall4": 0,
      "total": 0
    },
    {
      "slotStart": "22:00",
      "slotEnd": "22:05",
      "flightFactor": 0.9876543209876543,
      "stall1": 0,
      "stall2": 0,
      "stall3": 0,
      "stall4": 0,
      "total": 0
    },
    {
      "slotStart": "22:05",
      "slotEnd": "22:10",
      "flightFactor": 2.271604938271605,
      "stall1": 0,
      "stall2": 0,
      "stall3": 0,
      "stall4": 0,
      "total": 0
    },
    {
      "slotStart": "22:10",
      "slotEnd": "22:15",
      "flightFactor": 0.3950617283950617,
      "stall1": 0,
      "stall2": 0,
      "stall3": 0,
      "stall4": 0,
      "total": 0
    },
    {
      "slotStart": "22:15",
      "slotEnd": "22:20",
      "flightFactor": 1.5802469135802468,
      "stall1": 0,
      "stall2": 0,
      "stall3": 0,
      "stall4": 0,
      "total": 0
    },
    {
      "slotStart": "22:20",
      "slotEnd": "22:25",
      "flightFactor": 0.691358024691358,
      "stall1": 0,
      "stall2": 0,
      "stall3": 0,
      "stall4": 0,
      "total": 0
    },
    {
      "slotStart": "22:25",
      "slotEnd": "22:30",
      "flightFactor": 0.691358024691358,
      "stall1": 0,
      "stall2": 0,
      "stall3": 0,
      "stall4": 0,
      "total": 0
    },
    {
      "slotStart": "22:30",
      "slotEnd": "22:35",
      "flightFactor": 0.8888888888888888,
      "stall1": 0,
      "stall2": 0,
      "stall3": 0,
      "stall4": 0,
      "total": 0
    },
    {
      "slotStart": "22:35",
      "slotEnd": "22:40",
      "flightFactor": 1.382716049382716,
      "stall1": 0,
      "stall2": 0,
      "stall3": 0,
      "stall4": 0,
      "total": 0
    },
    {
      "slotStart": "22:40",
      "slotEnd": "22:45",
      "flightFactor": 0.691358024691358,
      "stall1": 0,
      "stall2": 0,
      "stall3": 0,
      "stall4": 0,
      "total": 0
    },
    {
      "slotStart": "22:45",
      "slotEnd": "22:50",
      "flightFactor": 0.8888888888888888,
      "stall1": 0,
      "stall2": 0,
      "stall3": 0,
      "stall4": 0,
      "total": 0
    },
    {
      "slotStart": "22:50",
      "slotEnd": "22:55",
      "flightFactor": 1.876543209876543,
      "stall1": 0,
      "stall2": 0,
      "stall3": 0,
      "stall4": 0,
      "total": 0
    },
    {
      "slotStart": "22:55",
      "slotEnd": "23:00",
      "flightFactor": 0.691358024691358,
      "stall1": 0,
      "stall2": 0,
      "stall3": 0,
      "stall4": 0,
      "total": 0
    },
    {
      "slotStart": "23:00",
      "slotEnd": "23:05",
      "flightFactor": 1.2839506172839505,
      "stall1": 0,
      "stall2": 0,
      "stall3": 0,
      "stall4": 0,
      "total": 0
    },
    {
      "slotStart": "23:05",
      "slotEnd": "23:10",
      "flightFactor": 0.7901234567901234,
      "stall1": 0,
      "stall2": 0,
      "stall3": 0,
      "stall4": 0,
      "total": 0
    },
    {
      "slotStart": "23:10",
      "slotEnd": "23:15",
      "flightFactor": 0.691358024691358,
      "stall1": 0,
      "stall2": 0,
      "stall3": 0,
      "stall4": 0,
      "total": 0
    },
    {
      "slotStart": "23:15",
      "slotEnd": "23:20",
      "flightFactor": 0.5925925925925926,
      "stall1": 0,
      "stall2": 0,
      "stall3": 0,
      "stall4": 0,
      "total": 0
    },
    {
      "slotStart": "23:20",
      "slotEnd": "23:25",
      "flightFactor": 0.8888888888888888,
      "stall1": 0,
      "stall2": 0,
      "stall3": 0,
      "stall4": 0,
      "total": 0
    },
    {
      "slotStart": "23:25",
      "slotEnd": "23:30",
      "flightFactor": 0.49382716049382713,
      "stall1": 0,
      "stall2": 0,
      "stall3": 0,
      "stall4": 0,
      "total": 0
    },
    {
      "slotStart": "23:30",
      "slotEnd": "23:35",
      "flightFactor": 0.691358024691358,
      "stall1": 0,
      "stall2": 0,
      "stall3": 0,
      "stall4": 0,
      "total": 0
    },
    {
      "slotStart": "23:35",
      "slotEnd": "23:40",
      "flightFactor": 0.3,
      "stall1": 0,
      "stall2": 0,
      "stall3": 0,
      "stall4": 0,
      "total": 0
    }
  ],
  "throughputScaleK": 5
}
