{
  "schemaVersion": 1,
  "generatedAt": "2026-05-18T15:48:06+09:00",
  "trendFactor": 0.8070796460176992,
  "trendWindow": {
    "actual": 76,
    "expected": 18.833333333333332,
    "ticks": 12,
    "source": "track",
    "k": 5
  },
  "baselineSampleCount": 996,
  "slots": [
    {
      "slotStart": "15:50",
      "slotEnd": "15:55",
      "flightFactor": 0.691358024691358,
      "stall1": 0,
      "stall2": 0,
      "stall3": 0,
      "stall4": 0,
      "total": 0
    },
    {
      "slotStart": "15:55",
      "slotEnd": "16:00",
      "flightFactor": 1.6790123456790123,
      "stall1": 5,
      "stall2": 5,
      "stall3": 0,
      "stall4": 0,
      "total": 10
    },
    {
      "slotStart": "16:00",
      "slotEnd": "16:05",
      "flightFactor": 0.691358024691358,
      "stall1": 0,
      "stall2": 0,
      "stall3": 0,
      "stall4": 0,
      "total": 0
    },
    {
      "slotStart": "16:05",
      "slotEnd": "16:10",
      "flightFactor": 0.5925925925925926,
      "stall1": 0,
      "stall2": 0,
      "stall3": 0,
      "stall4": 0,
      "total": 0
    },
    {
      "slotStart": "16:10",
      "slotEnd": "16:15",
      "flightFactor": 2.4691358024691357,
      "stall1": 0,
      "stall2": 5,
      "stall3": 0,
      "stall4": 0,
      "total": 5
    },
    {
      "slotStart": "16:15",
      "slotEnd": "16:20",
      "flightFactor": 0.9876543209876543,
      "stall1": 5,
      "stall2": 0,
      "stall3": 0,
      "stall4": 0,
      "total": 5
    },
    {
      "slotStart": "16:20",
      "slotEnd": "16:25",
      "flightFactor": 0.3950617283950617,
      "stall1": 0,
      "stall2": 0,
      "stall3": 0,
      "stall4": 0,
      "total": 0
    },
    {
      "slotStart": "16:25",
      "slotEnd": "16:30",
      "flightFactor": 0.9876543209876543,
      "stall1": 0,
      "stall2": 0,
      "stall3": 0,
      "stall4": 0,
      "total": 0
    },
    {
      "slotStart": "16:30",
      "slotEnd": "16:35",
      "flightFactor": 0.5925925925925926,
      "stall1": 0,
      "stall2": 0,
      "stall3": 0,
      "stall4": 0,
      "total": 0
    },
    {
      "slotStart": "16:35",
      "slotEnd": "16:40",
      "flightFactor": 0.3,
      "stall1": 0,
      "stall2": 0,
      "stall3": 0,
      "stall4": 0,
      "total": 0
    },
    {
      "slotStart": "16:40",
      "slotEnd": "16:45",
      "flightFactor": 0.691358024691358,
      "stall1": 0,
      "stall2": 0,
      "stall3": 0,
      "stall4": 0,
      "total": 0
    },
    {
      "slotStart": "16:45",
      "slotEnd": "16:50",
      "flightFactor": 1.7777777777777777,
      "stall1": 0,
      "stall2": 0,
      "stall3": 5,
      "stall4": 0,
      "total": 5
    },
    {
      "slotStart": "16:50",
      "slotEnd": "16:55",
      "flightFactor": 0.3,
      "stall1": 0,
      "stall2": 0,
      "stall3": 0,
      "stall4": 0,
      "total": 0
    },
    {
      "slotStart": "16:55",
      "slotEnd": "17:00",
      "flightFactor": 1.0864197530864197,
      "stall1": 0,
      "stall2": 0,
      "stall3": 0,
      "stall4": 0,
      "total": 0
    },
    {
      "slotStart": "17:00",
      "slotEnd": "17:05",
      "flightFactor": 1.9753086419753085,
      "stall1": 5,
      "stall2": 0,
      "stall3": 0,
      "stall4": 0,
      "total": 5
    },
    {
      "slotStart": "17:05",
      "slotEnd": "17:10",
      "flightFactor": 0.3,
      "stall1": 0,
      "stall2": 0,
      "stall3": 0,
      "stall4": 0,
      "total": 0
    },
    {
      "slotStart": "17:10",
      "slotEnd": "17:15",
      "flightFactor": 1.6790123456790123,
      "stall1": 0,
      "stall2": 0,
      "stall3": 0,
      "stall4": 0,
      "total": 0
    },
    {
      "slotStart": "17:15",
      "slotEnd": "17:20",
      "flightFactor": 0.8888888888888888,
      "stall1": 0,
      "stall2": 0,
      "stall3": 0,
      "stall4": 0,
      "total": 0
    },
    {
      "slotStart": "17:20",
      "slotEnd": "17:25",
      "flightFactor": 0.3,
      "stall1": 0,
      "stall2": 0,
      "stall3": 0,
      "stall4": 0,
      "total": 0
    },
    {
      "slotStart": "17:25",
      "slotEnd": "17:30",
      "flightFactor": 0.691358024691358,
      "stall1": 0,
      "stall2": 0,
      "stall3": 0,
      "stall4": 0,
      "total": 0
    },
    {
      "slotStart": "17:30",
      "slotEnd": "17:35",
      "flightFactor": 0.3,
      "stall1": 0,
      "stall2": 0,
      "stall3": 0,
      "stall4": 0,
      "total": 0
    },
    {
      "slotStart": "17:35",
      "slotEnd": "17:40",
      "flightFactor": 0.3950617283950617,
      "stall1": 0,
      "stall2": 0,
      "stall3": 0,
      "stall4": 0,
      "total": 0
    },
    {
      "slotStart": "17:40",
      "slotEnd": "17:45",
      "flightFactor": 3,
      "stall1": 0,
      "stall2": 5,
      "stall3": 15,
      "stall4": 0,
      "total": 20
    },
    {
      "slotStart": "17:45",
      "slotEnd": "17:50",
      "flightFactor": 0.5925925925925926,
      "stall1": 0,
      "stall2": 0,
      "stall3": 0,
      "stall4": 0,
      "total": 0
    }
  ],
  "throughputScaleK": 5
}
