{
  "schemaVersion": 1,
  "generatedAt": "2026-05-21T19:51:46+09:00",
  "trendFactor": 1,
  "trendWindow": {
    "actual": 0,
    "expected": 0,
    "ticks": 12,
    "levelSource": "track-anchored"
  },
  "baselineSampleCount": 1533,
  "slots": [
    {
      "slotStart": "19:55",
      "slotEnd": "20:00",
      "flightFactor": 0.7826086956521738,
      "stall1": 1,
      "stall2": 1,
      "stall3": 1,
      "stall4": 1,
      "total": 4
    },
    {
      "slotStart": "20:00",
      "slotEnd": "20:05",
      "flightFactor": 0.3,
      "stall1": 0,
      "stall2": 0,
      "stall3": 0,
      "stall4": 0,
      "total": 0
    },
    {
      "slotStart": "20:05",
      "slotEnd": "20:10",
      "flightFactor": 0.9130434782608695,
      "stall1": 1,
      "stall2": 1,
      "stall3": 1,
      "stall4": 2,
      "total": 5
    },
    {
      "slotStart": "20:10",
      "slotEnd": "20:15",
      "flightFactor": 0.3,
      "stall1": 0,
      "stall2": 0,
      "stall3": 0,
      "stall4": 0,
      "total": 0
    },
    {
      "slotStart": "20:15",
      "slotEnd": "20:20",
      "flightFactor": 0.3,
      "stall1": 0,
      "stall2": 0,
      "stall3": 0,
      "stall4": 0,
      "total": 0
    },
    {
      "slotStart": "20:20",
      "slotEnd": "20:25",
      "flightFactor": 2.0869565217391304,
      "stall1": 3,
      "stall2": 2,
      "stall3": 2,
      "stall4": 3,
      "total": 10
    },
    {
      "slotStart": "20:25",
      "slotEnd": "20:30",
      "flightFactor": 2.4782608695652173,
      "stall1": 3,
      "stall2": 2,
      "stall3": 2,
      "stall4": 3,
      "total": 10
    },
    {
      "slotStart": "20:30",
      "slotEnd": "20:35",
      "flightFactor": 0.7826086956521738,
      "stall1": 1,
      "stall2": 1,
      "stall3": 1,
      "stall4": 1,
      "total": 4
    },
    {
      "slotStart": "20:35",
      "slotEnd": "20:40",
      "flightFactor": 1.3043478260869565,
      "stall1": 2,
      "stall2": 1,
      "stall3": 1,
      "stall4": 2,
      "total": 6
    },
    {
      "slotStart": "20:40",
      "slotEnd": "20:45",
      "flightFactor": 1.434782608695652,
      "stall1": 2,
      "stall2": 1,
      "stall3": 1,
      "stall4": 3,
      "total": 7
    },
    {
      "slotStart": "20:45",
      "slotEnd": "20:50",
      "flightFactor": 0.3,
      "stall1": 0,
      "stall2": 0,
      "stall3": 0,
      "stall4": 0,
      "total": 0
    },
    {
      "slotStart": "20:50",
      "slotEnd": "20:55",
      "flightFactor": 1.434782608695652,
      "stall1": 2,
      "stall2": 1,
      "stall3": 1,
      "stall4": 3,
      "total": 7
    },
    {
      "slotStart": "20:55",
      "slotEnd": "21:00",
      "flightFactor": 0.3,
      "stall1": 0,
      "stall2": 0,
      "stall3": 0,
      "stall4": 0,
      "total": 0
    },
    {
      "slotStart": "21:00",
      "slotEnd": "21:05",
      "flightFactor": 1.3043478260869565,
      "stall1": 2,
      "stall2": 1,
      "stall3": 1,
      "stall4": 2,
      "total": 6
    },
    {
      "slotStart": "21:05",
      "slotEnd": "21:10",
      "flightFactor": 0.9130434782608695,
      "stall1": 1,
      "stall2": 1,
      "stall3": 1,
      "stall4": 2,
      "total": 5
    },
    {
      "slotStart": "21:10",
      "slotEnd": "21:15",
      "flightFactor": 0.6521739130434783,
      "stall1": 1,
      "stall2": 1,
      "stall3": 1,
      "stall4": 1,
      "total": 4
    },
    {
      "slotStart": "21:15",
      "slotEnd": "21:20",
      "flightFactor": 1.1739130434782608,
      "stall1": 2,
      "stall2": 1,
      "stall3": 1,
      "stall4": 2,
      "total": 6
    },
    {
      "slotStart": "21:20",
      "slotEnd": "21:25",
      "flightFactor": 0.3,
      "stall1": 0,
      "stall2": 0,
      "stall3": 0,
      "stall4": 0,
      "total": 0
    },
    {
      "slotStart": "21:25",
      "slotEnd": "21:30",
      "flightFactor": 0.3,
      "stall1": 0,
      "stall2": 0,
      "stall3": 0,
      "stall4": 0,
      "total": 0
    },
    {
      "slotStart": "21:30",
      "slotEnd": "21:35",
      "flightFactor": 3,
      "stall1": 3,
      "stall2": 2,
      "stall3": 2,
      "stall4": 3,
      "total": 10
    },
    {
      "slotStart": "21:35",
      "slotEnd": "21:40",
      "flightFactor": 2.4782608695652173,
      "stall1": 3,
      "stall2": 2,
      "stall3": 2,
      "stall4": 3,
      "total": 10
    },
    {
      "slotStart": "21:40",
      "slotEnd": "21:45",
      "flightFactor": 0.3,
      "stall1": 0,
      "stall2": 0,
      "stall3": 0,
      "stall4": 0,
      "total": 0
    },
    {
      "slotStart": "21:45",
      "slotEnd": "21:50",
      "flightFactor": 0.3913043478260869,
      "stall1": 1,
      "stall2": 0,
      "stall3": 0,
      "stall4": 1,
      "total": 2
    },
    {
      "slotStart": "21:50",
      "slotEnd": "21:55",
      "flightFactor": 1.3043478260869565,
      "stall1": 2,
      "stall2": 1,
      "stall3": 1,
      "stall4": 2,
      "total": 6
    }
  ],
  "throughputScaleK": 1
}
