{
  "updatedAt": "2026-05-17T11:00:34+09:00",
  "source": "Open-Meteo (api.open-meteo.com)",
  "current": {
    "weatherCode": 0,
    "lightningActive": false,
    "temperature": 24.5,
    "precipitation": 0,
    "cloudCover": 0
  },
  "lastLightningEndedAt": null,
  "lightningRecoveryStartHHMM": null,
  "history15min": [
    {
      "time": "2026-05-17T08:15",
      "weatherCode": 0,
      "isLightning": false
    },
    {
      "time": "2026-05-17T08:30",
      "weatherCode": 0,
      "isLightning": false
    },
    {
      "time": "2026-05-17T08:45",
      "weatherCode": 0,
      "isLightning": false
    },
    {
      "time": "2026-05-17T09:00",
      "weatherCode": 0,
      "isLightning": false
    },
    {
      "time": "2026-05-17T09:15",
      "weatherCode": 0,
      "isLightning": false
    },
    {
      "time": "2026-05-17T09:30",
      "weatherCode": 0,
      "isLightning": false
    },
    {
      "time": "2026-05-17T09:45",
      "weatherCode": 0,
      "isLightning": false
    },
    {
      "time": "2026-05-17T10:00",
      "weatherCode": 0,
      "isLightning": false
    },
    {
      "time": "2026-05-17T10:15",
      "weatherCode": 0,
      "isLightning": false
    },
    {
      "time": "2026-05-17T10:30",
      "weatherCode": 0,
      "isLightning": false
    },
    {
      "time": "2026-05-17T10:45",
      "weatherCode": 0,
      "isLightning": false
    },
    {
      "time": "2026-05-17T11:00",
      "weatherCode": 0,
      "isLightning": false
    }
  ]
}