{
  "updatedAt": "2026-04-29T17:39:08+09:00",
  "source": "Open-Meteo (api.open-meteo.com)",
  "current": {
    "weatherCode": 2,
    "lightningActive": false,
    "temperature": 15.9,
    "precipitation": 0,
    "cloudCover": 79
  },
  "lastLightningEndedAt": null,
  "lightningRecoveryStartHHMM": null,
  "history15min": [
    {
      "time": "2026-04-29T14:45",
      "weatherCode": 2,
      "isLightning": false
    },
    {
      "time": "2026-04-29T15:00",
      "weatherCode": 2,
      "isLightning": false
    },
    {
      "time": "2026-04-29T15:15",
      "weatherCode": 2,
      "isLightning": false
    },
    {
      "time": "2026-04-29T15:30",
      "weatherCode": 2,
      "isLightning": false
    },
    {
      "time": "2026-04-29T15:45",
      "weatherCode": 2,
      "isLightning": false
    },
    {
      "time": "2026-04-29T16:00",
      "weatherCode": 2,
      "isLightning": false
    },
    {
      "time": "2026-04-29T16:15",
      "weatherCode": 2,
      "isLightning": false
    },
    {
      "time": "2026-04-29T16:30",
      "weatherCode": 2,
      "isLightning": false
    },
    {
      "time": "2026-04-29T16:45",
      "weatherCode": 2,
      "isLightning": false
    },
    {
      "time": "2026-04-29T17:00",
      "weatherCode": 2,
      "isLightning": false
    },
    {
      "time": "2026-04-29T17:15",
      "weatherCode": 2,
      "isLightning": false
    },
    {
      "time": "2026-04-29T17:30",
      "weatherCode": 3,
      "isLightning": false
    }
  ]
}